mc2p/__init__.py
mc2p/base.py
mc2p/errors.py
mc2p/mc2p.py
mc2p/mixin.py
mc2p/notification.py
mc2p/objects.py
mc2p/request.py
mc2p/resources.py
mc2p/utils.py
mc2p_python-0.1.4.dist-info/LICENSE.md
mc2p_python-0.1.4.dist-info/METADATA
mc2p_python-0.1.4.dist-info/WHEEL
mc2p_python-0.1.4.dist-info/top_level.txt
mc2p_python-0.1.4.dist-info/RECORD
